setup.py
wgy_distributions/Binomialdistribution.py
wgy_distributions/Gaussiandistribution.py
wgy_distributions/Generaldistribution.py
wgy_distributions/__init__.py
wgy_distributions.egg-info/PKG-INFO
wgy_distributions.egg-info/SOURCES.txt
wgy_distributions.egg-info/dependency_links.txt
wgy_distributions.egg-info/not-zip-safe
wgy_distributions.egg-info/top_level.txt